Workbook

Sheet Premissas
B2: Prestare — Gestão · Premissas de preço
B3: Edite apenas as células em amarelo. Tudo o mais é fórmula.
B5: Plano | C5: Valor base / mês | D5: Valor por unidade / mês | E5: Taxa de implantação
B6: Essencial | C6: 149 | D6: 2 | E6: 290
B7: Profissional | C7: 297 | D7: 2.8 | E7: 490
B8: Elite | C8: 497 | D8: 3.8 | E8: 790
B10: Plano usado no cenário desta planilha: | D10: Profissional
B12: Fonte dos valores: tabela de preços informada pelo cliente (Vinicius / Prestare) em 26/08/2026.
B13: Fonte das unidades: lista de condomínios da carteira Prestare informada pelo cliente.

Sheet Carteira
B2: Receita por condomínio — plano Profissional
B3: Mensalidade = valor base + (unidades × valor por unidade). Todas as células pretas são fórmulas.
B5: # | C5: Condomínio | D5: Unidades | E5: Mensalidade | F5: Custo por apto / mês | G5: Implantação | H5: 1º mês | I5: Receita 12 meses
B6: 1 | C6: Damha | D6: 308 | E6: =Premissas!$C$7+D6*Premissas!$D$7 -> 1159.4 | F6: =E6/D6 -> 3.7642857 | G6: =Premissas!$E$7 -> 490 | H6: =E6+G6 -> 1649.4 | I6: =E6*12 -> 13912.8
B7: 2 | C7: Ideal Life | D7: 200 | E7: =Premissas!$C$7+D7*Premissas!$D$7 -> 857 | F7: =E7/D7 -> 4.285 | G7: =Premissas!$E$7 -> 490 | H7: =E7+G7 -> 1347 | I7: =E7*12 -> 10284
B8: 3 | C8: Duarte Nogueira | D8: 160 | E8: =Premissas!$C$7+D8*Premissas!$D$7 -> 745 | F8: =E8/D8 -> 4.65625 | G8: =Premissas!$E$7 -> 490 | H8: =E8+G8 -> 1235 | I8: =E8*12 -> 8940
B9: 4 | C9: Jardim Alvorada | D9: 120 | E9: =Premissas!$C$7+D9*Premissas!$D$7 -> 633 | F9: =E9/D9 -> 5.275 | G9: =Premissas!$E$7 -> 490 | H9: =E9+G9 -> 1123 | I9: =E9*12 -> 7596
B10: 5 | C10: Casa Pienza | D10: 112 | E10: =Premissas!$C$7+D10*Premissas!$D$7 -> 610.6 | F10: =E10/D10 -> 5.4517857 | G10: =Premissas!$E$7 -> 490 | H10: =E10+G10 -> 1100.6 | I10: =E10*12 -> 7327.2
B11: 6 | C11: Solar dos Ipês | D11: 64 | E11: =Premissas!$C$7+D11*Premissas!$D$7 -> 476.2 | F11: =E11/D11 -> 7.440625 | G11: =Premissas!$E$7 -> 490 | H11: =E11+G11 -> 966.2 | I11: =E11*12 -> 5714.4
B12: 7 | C12: Moreschi | D12: 24 | E12: =Premissas!$C$7+D12*Premissas!$D$7 -> 364.2 | F12: =E12/D12 -> 15.175 | G12: =Premissas!$E$7 -> 490 | H12: =E12+G12 -> 854.2 | I12: =E12*12 -> 4370.4
B13: 8 | C13: Rio Negro | D13: 24 | E13: =Premissas!$C$7+D13*Premissas!$D$7 -> 364.2 | F13: =E13/D13 -> 15.175 | G13: =Premissas!$E$7 -> 490 | H13: =E13+G13 -> 854.2 | I13: =E13*12 -> 4370.4
B14: 9 | C14: Santa Andélia | D14: 24 | E14: =Premissas!$C$7+D14*Premissas!$D$7 -> 364.2 | F14: =E14/D14 -> 15.175 | G14: =Premissas!$E$7 -> 490 | H14: =E14+G14 -> 854.2 | I14: =E14*12 -> 4370.4
B15: 10 | C15: Veredas do Sol | D15: 22 | E15: =Premissas!$C$7+D15*Premissas!$D$7 -> 358.6 | F15: =E15/D15 -> 16.3 | G15: =Premissas!$E$7 -> 490 | H15: =E15+G15 -> 848.6 | I15: =E15*12 -> 4303.2
B16: 11 | C16: Grão Pará | D16: 20 | E16: =Premissas!$C$7+D16*Premissas!$D$7 -> 353 | F16: =E16/D16 -> 17.65 | G16: =Premissas!$E$7 -> 490 | H16: =E16+G16 -> 843 | I16: =E16*12 -> 4236
B17: 12 | C17: Santos Dumont | D17: 20 | E17: =Premissas!$C$7+D17*Premissas!$D$7 -> 353 | F17: =E17/D17 -> 17.65 | G17: =Premissas!$E$7 -> 490 | H17: =E17+G17 -> 843 | I17: =E17*12 -> 4236
... B20: 15 | C20: Porto Seguro | D20: 12 | E20: =Premissas!$C$7+D20*Premissas!$D$7 -> 330.6 | F20: =E20/D20 -> 27.55 | G20: =Premissas!$E$7 -> 490 | H20: =E20+G20 -> 820.6 | I20: =E20*12 -> 3967.2
C21: TOTAL DA CARTEIRA | D21: =SUM(D6:D20) -> 1141 | E21: =SUM(E6:E20) -> 7649.8 | F21: =E21/D21 -> 6.7044698 | G21: =SUM(G6:G20) -> 7350 | H21: =SUM(H6:H20) -> 14999.8 | I21: =SUM(I6:I20) -> 91797.6
C23: Média por condomínio | E23: =E21/15 -> 509.98667
C24: Média de unidades por condomínio | E24: =D21/15 -> 76.066667

Sheet Comparativo
B2: Mensalidade por condomínio nos três planos
B3: Serve para decidir onde subir para Elite e onde o Essencial faz mais sentido.
B5: Condomínio | C5: Unidades | D5: Essencial | E5: Profissional | F5: Elite | G5: Essencial / apto | H5: Profissional / apto | I5: Elite / apto
B6: =Carteira!C6 -> Damha | C6: =Carteira!D6 -> 308 | D6: =Premissas!$C$6+$C6*Premissas!$D$6 -> 765 | E6: =Premissas!$C$7+$C6*Premissas!$D$7 -> 1159.4 | F6: =Premissas!$C$8+$C6*Premissas!$D$8 -> 1667.4 | G6: =D6/$C6 -> 2.4837662 | H6: =E6/$C6 -> 3.7642857 | I6: =F6/$C6 -> 5.4136364
B7: =Carteira!C7 -> Ideal Life | C7: =Carteira!D7 -> 200 | D7: =Premissas!$C$6+$C7*Premissas!$D$6 -> 549 | E7: =Premissas!$C$7+$C7*Premissas!$D$7 -> 857 | F7: =Premissas!$C$8+$C7*Premissas!$D$8 -> 1257 | G7: =D7/$C7 -> 2.745 | H7: =E7/$C7 -> 4.285 | I7: =F7/$C7 -> 6.285
B8: =Carteira!C8 -> Duarte Nogueira | C8: =Carteira!D8 -> 160 | D8: =Premissas!$C$6+$C8*Premissas!$D$6 -> 469 | E8: =Premissas!$C$7+$C8*Premissas!$D$7 -> 745 | F8: =Premissas!$C$8+$C8*Premissas!$D$8 -> 1105 | G8: =D8/$C8 -> 2.93125 | H8: =E8/$C8 -> 4.65625 | I8: =F8/$C8 -> 6.90625
B9: =Carteira!C9 -> Jardim Alvorada | C9: =Carteira!D9 -> 120 | D9: =Premissas!$C$6+$C9*Premissas!$D$6 -> 389 | E9: =Premissas!$C$7+$C9*Premissas!$D$7 -> 633 | F9: =Premissas!$C$8+$C9*Premissas!$D$8 -> 953 | G9: =D9/$C9 -> 3.2416667 | H9: =E9/$C9 -> 5.275 | I9: =F9/$C9 -> 7.9416667
B10: =Carteira!C10 -> Casa Pienza | C10: =Carteira!D10 -> 112 | D10: =Premissas!$C$6+$C10*Premissas!$D$6 -> 373 | E10: =Premissas!$C$7+$C10*Premissas!$D$7 -> 610.6 | F10: =Premissas!$C$8+$C10*Premissas!$D$8 -> 922.6 | G10: =D10/$C10 -> 3.3303571 | H10: =E10/$C10 -> 5.4517857 | I10: =F10/$C10 -> 8.2375
B11: =Carteira!C11 -> Solar dos Ipês | C11: =Carteira!D11 -> 64 | D11: =Premissas!$C$6+$C11*Premissas!$D$6 -> 277 | E11: =Premissas!$C$7+$C11*Premissas!$D$7 -> 476.2 | F11: =Premissas!$C$8+$C11*Premissas!$D$8 -> 740.2 | G11: =D11/$C11 -> 4.328125 | H11: =E11/$C11 -> 7.440625 | I11: =F11/$C11 -> 11.565625
B12: =Carteira!C12 -> Moreschi | C12: =Carteira!D12 -> 24 | D12: =Premissas!$C$6+$C12*Premissas!$D$6 -> 197 | E12: =Premissas!$C$7+$C12*Premissas!$D$7 -> 364.2 | F12: =Premissas!$C$8+$C12*Premissas!$D$8 -> 588.2 | G12: =D12/$C12 -> 8.2083333 | H12: =E12/$C12 -> 15.175 | I12: =F12/$C12 -> 24.508333
B13: =Carteira!C13 -> Rio Negro | C13: =Carteira!D13 -> 24 | D13: =Premissas!$C$6+$C13*Premissas!$D$6 -> 197 | E13: =Premissas!$C$7+$C13*Premissas!$D$7 -> 364.2 | F13: =Premissas!$C$8+$C13*Premissas!$D$8 -> 588.2 | G13: =D13/$C13 -> 8.2083333 | H13: =E13/$C13 -> 15.175 | I13: =F13/$C13 -> 24.508333
B14: =Carteira!C14 -> Santa Andélia | C14: =Carteira!D14 -> 24 | D14: =Premissas!$C$6+$C14*Premissas!$D$6 -> 197 | E14: =Premissas!$C$7+$C14*Premissas!$D$7 -> 364.2 | F14: =Premissas!$C$8+$C14*Premissas!$D$8 -> 588.2 | G14: =D14/$C14 -> 8.2083333 | H14: =E14/$C14 -> 15.175 | I14: =F14/$C14 -> 24.508333
B15: =Carteira!C15 -> Veredas do Sol | C15: =Carteira!D15 -> 22 | D15: =Premissas!$C$6+$C15*Premissas!$D$6 -> 193 | E15: =Premissas!$C$7+$C15*Premissas!$D$7 -> 358.6 | F15: =Premissas!$C$8+$C15*Premissas!$D$8 -> 580.6 | G15: =D15/$C15 -> 8.7727273 | H15: =E15/$C15 -> 16.3 | I15: =F15/$C15 -> 26.390909
B16: =Carteira!C16 -> Grão Pará | C16: =Carteira!D16 -> 20 | D16: =Premissas!$C$6+$C16*Premissas!$D$6 -> 189 | E16: =Premissas!$C$7+$C16*Premissas!$D$7 -> 353 | F16: =Premissas!$C$8+$C16*Premissas!$D$8 -> 573 | G16: =D16/$C16 -> 9.45 | H16: =E16/$C16 -> 17.65 | I16: =F16/$C16 -> 28.65
B17: =Carteira!C17 -> Santos Dumont | C17: =Carteira!D17 -> 20 | D17: =Premissas!$C$6+$C17*Premissas!$D$6 -> 189 | E17: =Premissas!$C$7+$C17*Premissas!$D$7 -> 353 | F17: =Premissas!$C$8+$C17*Premissas!$D$8 -> 573 | G17: =D17/$C17 -> 9.45 | H17: =E17/$C17 -> 17.65 | I17: =F17/$C17 -> 28.65
... B20: =Carteira!C20 -> Porto Seguro | C20: =Carteira!D20 -> 12 | D20: =Premissas!$C$6+$C20*Premissas!$D$6 -> 173 | E20: =Premissas!$C$7+$C20*Premissas!$D$7 -> 330.6 | F20: =Premissas!$C$8+$C20*Premissas!$D$8 -> 542.6 | G20: =D20/$C20 -> 14.416667 | H20: =E20/$C20 -> 27.55 | I20: =F20/$C20 -> 45.216667
B21: TOTAL | C21: =SUM(C6:C20) -> 1141 | D21: =SUM(D6:D20) -> 4517 | E21: =SUM(E6:E20) -> 7649.8 | F21: =SUM(F6:F20) -> 11790.8

Sheet Cenários
B2: Quanto entra conforme a taxa de adesão da carteira
B3: Base: 15 condomínios, plano Profissional. Ajuste o percentual em amarelo.
B5: Cenário | C5: % da carteira que adere | D5: Condomínios | E5: MRR | F5: Receita 12 meses | G5: Implantação (única) | H5: Total ano 1
B6: Pessimista | C6: 0.4 | D6: =ROUND(C6*15,0) -> 6 | E6: =Carteira!$E$21*C6 -> 3059.92 | F6: =E6*12 -> 36719.04 | G6: =Premissas!$E$7*D6 -> 2940 | H6: =F6+G6 -> 39659.04
B7: Conservador | C7: 0.6 | D7: =ROUND(C7*15,0) -> 9 | E7: =Carteira!$E$21*C7 -> 4589.88 | F7: =E7*12 -> 55078.56 | G7: =Premissas!$E$7*D7 -> 4410 | H7: =F7+G7 -> 59488.56
B8: Provável | C8: 0.75 | D8: =ROUND(C8*15,0) -> 11 | E8: =Carteira!$E$21*C8 -> 5737.35 | F8: =E8*12 -> 68848.2 | G8: =Premissas!$E$7*D8 -> 5390 | H8: =F8+G8 -> 74238.2
B9: Carteira inteira | C9: 1 | D9: =ROUND(C9*15,0) -> 15 | E9: =Carteira!$E$21*C9 -> 7649.8 | F9: =E9*12 -> 91797.6 | G9: =Premissas!$E$7*D9 -> 7350 | H9: =F9+G9 -> 99147.6
B12: Observação
B13: Os 6 condomínios com 24 unidades ou menos custam mais de R$ 15 por apartamento/mês no Profissional, contra R$ 3,76 no Damha. Nesses casos, o Essencial (ou um piso de mensalidade) tende a ser a venda possível — a mensalidade cheia dificilmente passa na assembleia.
