Workbook

Sheet Como preencher
B2: Mapeamento de condomínios verticais — Catanduva/SP
B3: Esta planilha é uma ferramenta de campo, não uma lista pronta.
B5: AVISO IMPORTANTE
B6: Não existe lista pública, oficial e completa dos condomínios verticais de Catanduva. Nem a prefeitura publica esse cadastro. Por isso esta planilha vem com a ESTRUTURA e o MÉTODO, e não com nomes de prédios inventados — uma lista fabricada faria você perder semanas ligando para endereços que não existem.
B9: COMO LEVANTAR A LISTA — em ordem de retorno
B10: 1. Google Maps, bairro por bairro (a fonte principal). Abra o Maps, digite "edifício" ou "residencial" e navegue por cada bairro da aba Bairros. Use a visão de satélite: prédio se identifica de cima na hora. Anote nome e endereço. Uma tarde cobre o Centro e a Higienópolis, que concentram os verticais.
B12: 2. Portais imobiliários. Procure apartamentos à venda em Catanduva no OLX, Viva Real, Imovelweb e nas imobiliárias locais. Cada anúncio traz o nome do edifício e quase sempre o valor do condomínio — que é um bom indício do porte do prédio.
B14: 3. Cartório de Registro de Imóveis da comarca. Condomínio edilício tem convenção registrada. É a fonte mais completa que existe, e a consulta é pública (pode haver custo por certidão).
B16: 4. Corpo de Bombeiros / AVCB. Edifício com mais de determinada altura precisa de AVCB. A consulta pública do Corpo de Bombeiros lista edificações com projeto aprovado.
B18: 5. Prefeitura — Setor de Tributos / IPTU e Obras. Nem sempre liberam, mas vale pedir a relação de edificações multifamiliares. Se não liberarem a lista, muitas vezes confirmam caso a caso.
B20: 6. Porteiros e zeladores. Porteiro conhece o prédio da esquina e o nome do síndico de lá. É a forma mais rápida de conseguir contato, e a única que já entrega o telefone.
B22: 7. Fornecedores locais. Empresa de elevador, dedetizadora e jardineiro têm a lista inteira na cabeça. Vale trocar: você indica eles na sua rede, eles te apresentam os síndicos.
... B36: 40 condomínios mapeados por mês. Comece pelo Centro e pela Higienópolis: em cidade do porte de Catanduva, os prédios de 40 a 120 unidades — a sua faixa mais atrativa de preço — se concentram nessas regiões.

Sheet Preço
B2: Tabela de preço por zonas
B3: Mesma tabela da planilha de preços. Edite só o amarelo.
B6: Faixa | C6: Limite superior | D6: Valor | E6: Unidades
B7: Compacto | C7: 30 | D7: 298 | E7: Até 30 unidades
B8: Padrão | C8: 60 | D8: 9.9 | E8: Da 31ª à 60ª
B9: Plus | C9: 120 | D9: 8.9 | E9: Da 61ª à 120ª
B10: Corporativo | C10: — | D10: 11.9 | E10: Acima da 120ª
B12: Taxa de implantação (única) | D12: 490

Sheet Bairros
B2: Bairros de Catanduva — controle da varredura
B3: Marque cada bairro conforme for varrendo no Google Maps. Fonte da lista: GuiaMais (guiamais.com.br/bairros/catanduva-sp).
B6: # | C6: Bairro | D6: Varrido? | E6: Prédios encontrados | F6: Data | G6: Observações
B7: 1 | C7: Centro
B8: 2 | C8: Cohab Euclides Figueiredo
B9: 3 | C9: Conjunto Esportivo
B10: 4 | C10: Conjunto G Mestrinelli
B11: 5 | C11: Distrito Industrial Antônio Bozo
B12: 6 | C12: Higienópolis
B13: 7 | C13: Jardim Amêndola
B14: 8 | C14: Jardim Bela Vista
B15: 9 | C15: Jardim Belém
B16: 10 | C16: Jardim Bom Pastor
B17: 11 | C17: Jardim Bosque
B18: 12 | C18: Jardim Brasil
... B52: 46 | C52: Vila Stocco
C54: TOTAL DE PRÉDIOS ENCONTRADOS | E54: =SUM(E7:E52) -> 0

Sheet Mapeamento
B2: Mapeamento de prospects — condomínios verticais
B3: Preencha as colunas amarelas. Faixa, mensalidade e receita anual se calculam sozinhas.
B6: # | C6: Nome do edifício | D6: Bairro | E6: Endereço | F6: Unid. | G6: Blocos | H6: Síndico | I6: Telefone / WhatsApp | J6: Administradora atual | K6: Status | L6: Origem | M6: Faixa | N6: Mensalidade | O6: Receita 12 meses | P6: Observações
B7: 1 | M7: =IF(G7="","",IF(G7<=Preço!$C$7,Preço!$B$7,IF(G7<=Preço!$C$8,Preço!$B$8,IF(G7<=Preço!$C$9,Preço!$B$9,Preço!$B$10)))) | N7: =IF(G7="","",Preço!$D$7+MAX(0,MIN(G7,Preço!$C$8)-Preço!$C$7)*Preço!$D$8+MAX(0,MIN(G7,Preço!$C$9)-Preço!$C$8)*Preço!$D$9+MAX(0,G7-Preço!$C$9)*Preço!$D$10) | O7: =IF(G7="","",N7*12)
B8: 2 | M8: =IF(G8="","",IF(G8<=Preço!$C$7,Preço!$B$7,IF(G8<=Preço!$C$8,Preço!$B$8,IF(G8<=Preço!$C$9,Preço!$B$9,Preço!$B$10)))) | N8: =IF(G8="","",Preço!$D$7+MAX(0,MIN(G8,Preço!$C$8)-Preço!$C$7)*Preço!$D$8+MAX(0,MIN(G8,Preço!$C$9)-Preço!$C$8)*Preço!$D$9+MAX(0,G8-Preço!$C$9)*Preço!$D$10) | O8: =IF(G8="","",N8*12)
B9: 3 | M9: =IF(G9="","",IF(G9<=Preço!$C$7,Preço!$B$7,IF(G9<=Preço!$C$8,Preço!$B$8,IF(G9<=Preço!$C$9,Preço!$B$9,Preço!$B$10)))) | N9: =IF(G9="","",Preço!$D$7+MAX(0,MIN(G9,Preço!$C$8)-Preço!$C$7)*Preço!$D$8+MAX(0,MIN(G9,Preço!$C$9)-Preço!$C$8)*Preço!$D$9+MAX(0,G9-Preço!$C$9)*Preço!$D$10) | O9: =IF(G9="","",N9*12)
B10: 4 | M10: =IF(G10="","",IF(G10<=Preço!$C$7,Preço!$B$7,IF(G10<=Preço!$C$8,Preço!$B$8,IF(G10<=Preço!$C$9,Preço!$B$9,Preço!$B$10)))) | N10: =IF(G10="","",Preço!$D$7+MAX(0,MIN(G10,Preço!$C$8)-Preço!$C$7)*Preço!$D$8+MAX(0,MIN(G10,Preço!$C$9)-Preço!$C$8)*Preço!$D$9+MAX(0,G10-Preço!$C$9)*Preço!$D$10) | O10: =IF(G10="","",N10*12)
B11: 5 | M11: =IF(G11="","",IF(G11<=Preço!$C$7,Preço!$B$7,IF(G11<=Preço!$C$8,Preço!$B$8,IF(G11<=Preço!$C$9,Preço!$B$9,Preço!$B$10)))) | N11: =IF(G11="","",Preço!$D$7+MAX(0,MIN(G11,Preço!$C$8)-Preço!$C$7)*Preço!$D$8+MAX(0,MIN(G11,Preço!$C$9)-Preço!$C$8)*Preço!$D$9+MAX(0,G11-Preço!$C$9)*Preço!$D$10) | O11: =IF(G11="","",N11*12)
B12: 6 | M12: =IF(G12="","",IF(G12<=Preço!$C$7,Preço!$B$7,IF(G12<=Preço!$C$8,Preço!$B$8,IF(G12<=Preço!$C$9,Preço!$B$9,Preço!$B$10)))) | N12: =IF(G12="","",Preço!$D$7+MAX(0,MIN(G12,Preço!$C$8)-Preço!$C$7)*Preço!$D$8+MAX(0,MIN(G12,Preço!$C$9)-Preço!$C$8)*Preço!$D$9+MAX(0,G12-Preço!$C$9)*Preço!$D$10) | O12: =IF(G12="","",N12*12)
B13: 7 | M13: =IF(G13="","",IF(G13<=Preço!$C$7,Preço!$B$7,IF(G13<=Preço!$C$8,Preço!$B$8,IF(G13<=Preço!$C$9,Preço!$B$9,Preço!$B$10)))) | N13: =IF(G13="","",Preço!$D$7+MAX(0,MIN(G13,Preço!$C$8)-Preço!$C$7)*Preço!$D$8+MAX(0,MIN(G13,Preço!$C$9)-Preço!$C$8)*Preço!$D$9+MAX(0,G13-Preço!$C$9)*Preço!$D$10) | O13: =IF(G13="","",N13*12)
B14: 8 | M14: =IF(G14="","",IF(G14<=Preço!$C$7,Preço!$B$7,IF(G14<=Preço!$C$8,Preço!$B$8,IF(G14<=Preço!$C$9,Preço!$B$9,Preço!$B$10)))) | N14: =IF(G14="","",Preço!$D$7+MAX(0,MIN(G14,Preço!$C$8)-Preço!$C$7)*Preço!$D$8+MAX(0,MIN(G14,Preço!$C$9)-Preço!$C$8)*Preço!$D$9+MAX(0,G14-Preço!$C$9)*Preço!$D$10) | O14: =IF(G14="","",N14*12)
B15: 9 | M15: =IF(G15="","",IF(G15<=Preço!$C$7,Preço!$B$7,IF(G15<=Preço!$C$8,Preço!$B$8,IF(G15<=Preço!$C$9,Preço!$B$9,Preço!$B$10)))) | N15: =IF(G15="","",Preço!$D$7+MAX(0,MIN(G15,Preço!$C$8)-Preço!$C$7)*Preço!$D$8+MAX(0,MIN(G15,Preço!$C$9)-Preço!$C$8)*Preço!$D$9+MAX(0,G15-Preço!$C$9)*Preço!$D$10) | O15: =IF(G15="","",N15*12)
B16: 10 | M16: =IF(G16="","",IF(G16<=Preço!$C$7,Preço!$B$7,IF(G16<=Preço!$C$8,Preço!$B$8,IF(G16<=Preço!$C$9,Preço!$B$9,Preço!$B$10)))) | N16: =IF(G16="","",Preço!$D$7+MAX(0,MIN(G16,Preço!$C$8)-Preço!$C$7)*Preço!$D$8+MAX(0,MIN(G16,Preço!$C$9)-Preço!$C$8)*Preço!$D$9+MAX(0,G16-Preço!$C$9)*Preço!$D$10) | O16: =IF(G16="","",N16*12)
B17: 11 | M17: =IF(G17="","",IF(G17<=Preço!$C$7,Preço!$B$7,IF(G17<=Preço!$C$8,Preço!$B$8,IF(G17<=Preço!$C$9,Preço!$B$9,Preço!$B$10)))) | N17: =IF(G17="","",Preço!$D$7+MAX(0,MIN(G17,Preço!$C$8)-Preço!$C$7)*Preço!$D$8+MAX(0,MIN(G17,Preço!$C$9)-Preço!$C$8)*Preço!$D$9+MAX(0,G17-Preço!$C$9)*Preço!$D$10) | O17: =IF(G17="","",N17*12)
B18: 12 | M18: =IF(G18="","",IF(G18<=Preço!$C$7,Preço!$B$7,IF(G18<=Preço!$C$8,Preço!$B$8,IF(G18<=Preço!$C$9,Preço!$B$9,Preço!$B$10)))) | N18: =IF(G18="","",Preço!$D$7+MAX(0,MIN(G18,Preço!$C$8)-Preço!$C$7)*Preço!$D$8+MAX(0,MIN(G18,Preço!$C$9)-Preço!$C$8)*Preço!$D$9+MAX(0,G18-Preço!$C$9)*Preço!$D$10) | O18: =IF(G18="","",N18*12)
... B156: 150 | M156: =IF(G156="","",IF(G156<=Preço!$C$7,Preço!$B$7,IF(G156<=Preço!$C$8,Preço!$B$8,IF(G156<=Preço!$C$9,Preço!$B$9,Preço!$B$10)))) | N156: =IF(G156="","",Preço!$D$7+MAX(0,MIN(G156,Preço!$C$8)-Preço!$C$7)*Preço!$D$8+MAX(0,MIN(G156,Preço!$C$9)-Preço!$C$8)*Preço!$D$9+MAX(0,G156-Preço!$C$9)*Preço!$D$10) | O156: =IF(G156="","",N156*12)
C157: TOTAL DO PIPELINE MAPEADO | G157: =SUM(G7:G156) -> 0 | N157: =SUM(N7:N156) -> 0 | O157: =SUM(O7:O156) -> 0
C159: Prédios mapeados | G159: =COUNTA(C7:C156) -> 0
C160: Com nº de unidades preenchido | G160: =COUNT(G7:G156) -> 0
C161: Já fechados (status 7) | G161: =COUNTIF(K7:K156,"7 - Fechado") -> 0
C162: Potencial de MRR mapeado | G162: =N157 -> 0
C163: Potencial anual mapeado | G163: =O157 -> 0

Sheet Clientes atuais
B2: Já são clientes da Prestare — não prospectar
B3: Os 15 condomínios da carteira. Servem de referência de porte ao mapear os prédios da concorrência.
B6: # | C6: Condomínio | D6: Unidades | E6: Faixa | F6: Mensalidade | G6: Receita 12 meses
B7: 1 | C7: Damha | D7: 308 | E7: =IF(D7<=Preço!$C$7,Preço!$B$7,IF(D7<=Preço!$C$8,Preço!$B$8,IF(D7<=Preço!$C$9,Preço!$B$9,Preço!$B$10))) -> Corporativo | F7: =Preço!$D$7+MAX(0,MIN(D7,Preço!$C$8)-Preço!$C$7)*Preço!$D$8+MAX(0,MIN(D7,Preço!$C$9)-Preço!$C$8)*Preço!$D$9+MAX(0,D7-Preço!$C$9)*Preço!$D$10 -> 3366.2 | G7: =F7*12 -> 40394.4
B8: 2 | C8: Ideal Life | D8: 200 | E8: =IF(D8<=Preço!$C$7,Preço!$B$7,IF(D8<=Preço!$C$8,Preço!$B$8,IF(D8<=Preço!$C$9,Preço!$B$9,Preço!$B$10))) -> Corporativo | F8: =Preço!$D$7+MAX(0,MIN(D8,Preço!$C$8)-Preço!$C$7)*Preço!$D$8+MAX(0,MIN(D8,Preço!$C$9)-Preço!$C$8)*Preço!$D$9+MAX(0,D8-Preço!$C$9)*Preço!$D$10 -> 2081 | G8: =F8*12 -> 24972
B9: 3 | C9: Duarte Nogueira | D9: 160 | E9: =IF(D9<=Preço!$C$7,Preço!$B$7,IF(D9<=Preço!$C$8,Preço!$B$8,IF(D9<=Preço!$C$9,Preço!$B$9,Preço!$B$10))) -> Corporativo | F9: =Preço!$D$7+MAX(0,MIN(D9,Preço!$C$8)-Preço!$C$7)*Preço!$D$8+MAX(0,MIN(D9,Preço!$C$9)-Preço!$C$8)*Preço!$D$9+MAX(0,D9-Preço!$C$9)*Preço!$D$10 -> 1605 | G9: =F9*12 -> 19260
B10: 4 | C10: Jardim Alvorada | D10: 120 | E10: =IF(D10<=Preço!$C$7,Preço!$B$7,IF(D10<=Preço!$C$8,Preço!$B$8,IF(D10<=Preço!$C$9,Preço!$B$9,Preço!$B$10))) -> Plus | F10: =Preço!$D$7+MAX(0,MIN(D10,Preço!$C$8)-Preço!$C$7)*Preço!$D$8+MAX(0,MIN(D10,Preço!$C$9)-Preço!$C$8)*Preço!$D$9+MAX(0,D10-Preço!$C$9)*Preço!$D$10 -> 1129 | G10: =F10*12 -> 13548
B11: 5 | C11: Casa Pienza | D11: 112 | E11: =IF(D11<=Preço!$C$7,Preço!$B$7,IF(D11<=Preço!$C$8,Preço!$B$8,IF(D11<=Preço!$C$9,Preço!$B$9,Preço!$B$10))) -> Plus | F11: =Preço!$D$7+MAX(0,MIN(D11,Preço!$C$8)-Preço!$C$7)*Preço!$D$8+MAX(0,MIN(D11,Preço!$C$9)-Preço!$C$8)*Preço!$D$9+MAX(0,D11-Preço!$C$9)*Preço!$D$10 -> 1057.8 | G11: =F11*12 -> 12693.6
B12: 6 | C12: Solar dos Ipês | D12: 64 | E12: =IF(D12<=Preço!$C$7,Preço!$B$7,IF(D12<=Preço!$C$8,Preço!$B$8,IF(D12<=Preço!$C$9,Preço!$B$9,Preço!$B$10))) -> Plus | F12: =Preço!$D$7+MAX(0,MIN(D12,Preço!$C$8)-Preço!$C$7)*Preço!$D$8+MAX(0,MIN(D12,Preço!$C$9)-Preço!$C$8)*Preço!$D$9+MAX(0,D12-Preço!$C$9)*Preço!$D$10 -> 630.6 | G12: =F12*12 -> 7567.2
B13: 7 | C13: Moreschi | D13: 24 | E13: =IF(D13<=Preço!$C$7,Preço!$B$7,IF(D13<=Preço!$C$8,Preço!$B$8,IF(D13<=Preço!$C$9,Preço!$B$9,Preço!$B$10))) -> Compacto | F13: =Preço!$D$7+MAX(0,MIN(D13,Preço!$C$8)-Preço!$C$7)*Preço!$D$8+MAX(0,MIN(D13,Preço!$C$9)-Preço!$C$8)*Preço!$D$9+MAX(0,D13-Preço!$C$9)*Preço!$D$10 -> 298 | G13: =F13*12 -> 3576
B14: 8 | C14: Rio Negro | D14: 24 | E14: =IF(D14<=Preço!$C$7,Preço!$B$7,IF(D14<=Preço!$C$8,Preço!$B$8,IF(D14<=Preço!$C$9,Preço!$B$9,Preço!$B$10))) -> Compacto | F14: =Preço!$D$7+MAX(0,MIN(D14,Preço!$C$8)-Preço!$C$7)*Preço!$D$8+MAX(0,MIN(D14,Preço!$C$9)-Preço!$C$8)*Preço!$D$9+MAX(0,D14-Preço!$C$9)*Preço!$D$10 -> 298 | G14: =F14*12 -> 3576
B15: 9 | C15: Santa Andélia | D15: 24 | E15: =IF(D15<=Preço!$C$7,Preço!$B$7,IF(D15<=Preço!$C$8,Preço!$B$8,IF(D15<=Preço!$C$9,Preço!$B$9,Preço!$B$10))) -> Compacto | F15: =Preço!$D$7+MAX(0,MIN(D15,Preço!$C$8)-Preço!$C$7)*Preço!$D$8+MAX(0,MIN(D15,Preço!$C$9)-Preço!$C$8)*Preço!$D$9+MAX(0,D15-Preço!$C$9)*Preço!$D$10 -> 298 | G15: =F15*12 -> 3576
B16: 10 | C16: Veredas do Sol | D16: 22 | E16: =IF(D16<=Preço!$C$7,Preço!$B$7,IF(D16<=Preço!$C$8,Preço!$B$8,IF(D16<=Preço!$C$9,Preço!$B$9,Preço!$B$10))) -> Compacto | F16: =Preço!$D$7+MAX(0,MIN(D16,Preço!$C$8)-Preço!$C$7)*Preço!$D$8+MAX(0,MIN(D16,Preço!$C$9)-Preço!$C$8)*Preço!$D$9+MAX(0,D16-Preço!$C$9)*Preço!$D$10 -> 298 | G16: =F16*12 -> 3576
B17: 11 | C17: Grão Pará | D17: 20 | E17: =IF(D17<=Preço!$C$7,Preço!$B$7,IF(D17<=Preço!$C$8,Preço!$B$8,IF(D17<=Preço!$C$9,Preço!$B$9,Preço!$B$10))) -> Compacto | F17: =Preço!$D$7+MAX(0,MIN(D17,Preço!$C$8)-Preço!$C$7)*Preço!$D$8+MAX(0,MIN(D17,Preço!$C$9)-Preço!$C$8)*Preço!$D$9+MAX(0,D17-Preço!$C$9)*Preço!$D$10 -> 298 | G17: =F17*12 -> 3576
B18: 12 | C18: Santos Dumont | D18: 20 | E18: =IF(D18<=Preço!$C$7,Preço!$B$7,IF(D18<=Preço!$C$8,Preço!$B$8,IF(D18<=Preço!$C$9,Preço!$B$9,Preço!$B$10))) -> Compacto | F18: =Preço!$D$7+MAX(0,MIN(D18,Preço!$C$8)-Preço!$C$7)*Preço!$D$8+MAX(0,MIN(D18,Preço!$C$9)-Preço!$C$8)*Preço!$D$9+MAX(0,D18-Preço!$C$9)*Preço!$D$10 -> 298 | G18: =F18*12 -> 3576
... B21: 15 | C21: Porto Seguro | D21: 12 | E21: =IF(D21<=Preço!$C$7,Preço!$B$7,IF(D21<=Preço!$C$8,Preço!$B$8,IF(D21<=Preço!$C$9,Preço!$B$9,Preço!$B$10))) -> Compacto | F21: =Preço!$D$7+MAX(0,MIN(D21,Preço!$C$8)-Preço!$C$7)*Preço!$D$8+MAX(0,MIN(D21,Preço!$C$9)-Preço!$C$8)*Preço!$D$9+MAX(0,D21-Preço!$C$9)*Preço!$D$10 -> 298 | G21: =F21*12 -> 3576
C22: TOTAL | D22: =SUM(D7:D21) -> 1141 | F22: =SUM(F7:F21) -> 12551.6 | G22: =SUM(G7:G21) -> 150619.2
